{"type": "FeatureCollection", "features": [{"type": "Feature", "geometry": {"type": "Point", "coordinates": [12.4964, 41.9028]}, "properties": {"name": "billytacos_official - Italia (69)", "description": "### billytacos_official\n**Area:** Italia\n**Punti vendita:** 69", "_umap_options": {"color": "#666666", "iconClass": "Circle"}}}]}