{"type":"FeatureCollection","features":[{"type":"Feature","geometry":{"type":"Point","coordinates":[12.766693779816686,41.97989590021095]},"properties":{"name":"Lazio (393)","description":"<div style=\"font-family:'Nunito',Arial,sans-serif;max-width:320px;padding:8px;\"><h3 style=\"margin:0 0 6px 0;font-size:18px;color:#333;\">Lazio</h3><p style=\"margin:0 0 16px 0;font-size:13px;color:#666;font-weight:600;\">Regione — 393 punti vendita</p><div style=\"display:grid;grid-template-columns:repeat(3,1fr);gap:12px;text-align:center;\"><div><div style=\"width:52px;height:52px;border-radius:50%;background:#00A651;display:flex;align-items:center;justify-content:center;margin:0 auto;font-size:18px;font-weight:bold;color:#fff;border:2px solid #00A651;\">115</div><div style=\"font-size:11px;margin-top:6px;color:#444;font-weight:600;line-height:1.2;\">Alice Pizza</div></div><div><div style=\"width:52px;height:52px;border-radius:50%;background:#FFC72C;display:flex;align-items:center;justify-content:center;margin:0 auto;font-size:18px;font-weight:bold;color:#333;border:2px solid #FFC72C;\">107</div><div style=\"font-size:11px;margin-top:6px;color:#444;font-weight:600;line-height:1.2;\">McDonald's</div></div><div><div style=\"width:52px;height:52px;border-radius:50%;background:#FF8732;display:flex;align-items:center;justify-content:center;margin:0 auto;font-size:18px;font-weight:bold;color:#fff;border:2px solid #FF8732;\">62</div><div style=\"font-size:11px;margin-top:6px;color:#444;font-weight:600;line-height:1.2;\">Burger King</div></div><div><div style=\"width:52px;height:52px;border-radius:50%;background:#E4002B;display:flex;align-items:center;justify-content:center;margin:0 auto;font-size:18px;font-weight:bold;color:#fff;border:2px solid #E4002B;\">59</div><div style=\"font-size:11px;margin-top:6px;color:#444;font-weight:600;line-height:1.2;\">La Piadineria</div></div><div><div style=\"width:52px;height:52px;border-radius:50%;background:#F40027;display:flex;align-items:center;justify-content:center;margin:0 auto;font-size:18px;font-weight:bold;color:#fff;border:2px solid #F40027;\">23</div><div style=\"font-size:11px;margin-top:6px;color:#444;font-weight:600;line-height:1.2;\">KFC</div></div><div><div style=\"width:52px;height:52px;border-radius:50%;background:#8B4513;display:flex;align-items:center;justify-content:center;margin:0 auto;font-size:18px;font-weight:bold;color:#fff;border:2px solid #8B4513;\">16</div><div style=\"font-size:11px;margin-top:6px;color:#444;font-weight:600;line-height:1.2;\">Roadhouse</div></div><div><div style=\"width:52px;height:52px;border-radius:50%;background:#00704A;display:flex;align-items:center;justify-content:center;margin:0 auto;font-size:18px;font-weight:bold;color:#fff;border:2px solid #00704A;\">7</div><div style=\"font-size:11px;margin-top:6px;color:#444;font-weight:600;line-height:1.2;\">Starbucks</div></div><div><div style=\"width:52px;height:52px;border-radius:50%;background:#D4A017;display:flex;align-items:center;justify-content:center;margin:0 auto;font-size:18px;font-weight:bold;color:#333;border:2px solid #D4A017;\">4</div><div style=\"font-size:11px;margin-top:6px;color:#444;font-weight:600;line-height:1.2;\">Billy Tacos</div></div><div style=\"visibility:hidden;\"><div style=\"width:52px;height:52px;\"></div><div style=\"font-size:10px;\">-</div></div></div></div>","_regione":"Lazio","_level":"regione","_umap_options":{"color":"#00A651","iconClass":"Circle"}}}]}