{"type":"FeatureCollection","features":[{"type":"Feature","geometry":{"type":"Point","coordinates":[12.766693779816686,41.97989590021095]},"properties":{"name":"Lazio (393)","description":"<div style=\"font-family:Arial,sans-serif;max-width:320px;\"><h3 style=\"margin:0 0 4px 0;font-size:16px;\">Lazio</h3><p style=\"margin:0 0 10px 0;font-size:12px;color:#666;\">Regione — 393 punti vendita</p><div style=\"display:grid;grid-template-columns:repeat(3,1fr);gap:10px 8px;text-align:center;\"><div><div style=\"width:52px;height:52px;border-radius:50%;background:#00A651;display:flex;align-items:center;justify-content:center;margin:0 auto;font-size:18px;font-weight:bold;color:#fff;box-shadow:0 2px 6px rgba(0,0,0,0.2);\">115</div><div style=\"font-size:10px;margin-top:3px;color:#333;line-height:1.2;\">Alice Pizza</div></div><div><div style=\"width:52px;height:52px;border-radius:50%;background:#FFC72C;display:flex;align-items:center;justify-content:center;margin:0 auto;font-size:18px;font-weight:bold;color:#333;box-shadow:0 2px 6px rgba(0,0,0,0.2);\">107</div><div style=\"font-size:10px;margin-top:3px;color:#333;line-height:1.2;\">McDonald's</div></div><div><div style=\"width:52px;height:52px;border-radius:50%;background:#FF8732;display:flex;align-items:center;justify-content:center;margin:0 auto;font-size:18px;font-weight:bold;color:#fff;box-shadow:0 2px 6px rgba(0,0,0,0.2);\">62</div><div style=\"font-size:10px;margin-top:3px;color:#333;line-height:1.2;\">Burger King</div></div><div><div style=\"width:52px;height:52px;border-radius:50%;background:#E4002B;display:flex;align-items:center;justify-content:center;margin:0 auto;font-size:18px;font-weight:bold;color:#fff;box-shadow:0 2px 6px rgba(0,0,0,0.2);\">59</div><div style=\"font-size:10px;margin-top:3px;color:#333;line-height:1.2;\">La Piadineria</div></div><div><div style=\"width:52px;height:52px;border-radius:50%;background:#F40027;display:flex;align-items:center;justify-content:center;margin:0 auto;font-size:18px;font-weight:bold;color:#fff;box-shadow:0 2px 6px rgba(0,0,0,0.2);\">23</div><div style=\"font-size:10px;margin-top:3px;color:#333;line-height:1.2;\">KFC</div></div><div><div style=\"width:52px;height:52px;border-radius:50%;background:#8B4513;display:flex;align-items:center;justify-content:center;margin:0 auto;font-size:18px;font-weight:bold;color:#fff;box-shadow:0 2px 6px rgba(0,0,0,0.2);\">16</div><div style=\"font-size:10px;margin-top:3px;color:#333;line-height:1.2;\">Roadhouse</div></div><div><div style=\"width:52px;height:52px;border-radius:50%;background:#00704A;display:flex;align-items:center;justify-content:center;margin:0 auto;font-size:18px;font-weight:bold;color:#fff;box-shadow:0 2px 6px rgba(0,0,0,0.2);\">7</div><div style=\"font-size:10px;margin-top:3px;color:#333;line-height:1.2;\">Starbucks</div></div><div><div style=\"width:52px;height:52px;border-radius:50%;background:#D4A017;display:flex;align-items:center;justify-content:center;margin:0 auto;font-size:18px;font-weight:bold;color:#333;box-shadow:0 2px 6px rgba(0,0,0,0.2);\">4</div><div style=\"font-size:10px;margin-top:3px;color:#333;line-height:1.2;\">Billy Tacos</div></div><div style=\"visibility:hidden;\"><div style=\"width:52px;height:52px;\"></div><div style=\"font-size:10px;\">-</div></div></div></div>","_regione":"Lazio","_level":"regione","_umap_options":{"color":"#00A651","iconClass":"Ball"}}}]}