{"type":"FeatureCollection","features":[{"type":"Feature","geometry":{"type":"Point","coordinates":[14.662583024691116,41.56767163311976]},"properties":{"name":"Campobasso (1)","description":"<div style=\"font-family:'Nunito',Arial,sans-serif;max-width:320px;padding:8px;\"><h3 style=\"margin:0 0 6px 0;font-size:18px;color:#333;\">Campobasso</h3><p style=\"margin:0 0 16px 0;font-size:13px;color:#666;font-weight:600;\">Comune — 1 punti vendita</p><div style=\"display:grid;grid-template-columns:repeat(3,1fr);gap:12px;text-align:center;\"><div><div style=\"width:52px;height:52px;border-radius:50%;background:#FFC72C;display:flex;align-items:center;justify-content:center;margin:0 auto;font-size:18px;font-weight:bold;color:#333;border:2px solid #FFC72C;\">1</div><div style=\"font-size:11px;margin-top:6px;color:#444;font-weight:600;line-height:1.2;\">McDonald's</div></div><div style=\"visibility:hidden;\"><div style=\"width:52px;height:52px;\"></div><div style=\"font-size:10px;\">-</div></div><div style=\"visibility:hidden;\"><div style=\"width:52px;height:52px;\"></div><div style=\"font-size:10px;\">-</div></div></div></div>","_regione":"Molise","_level":"comune","_umap_options":{"color":"#FFC72C","iconClass":"Circle"}}},{"type":"Feature","geometry":{"type":"Point","coordinates":[14.216179508836648,41.60724606253518]},"properties":{"name":"Isernia (1)","description":"<div style=\"font-family:'Nunito',Arial,sans-serif;max-width:320px;padding:8px;\"><h3 style=\"margin:0 0 6px 0;font-size:18px;color:#333;\">Isernia</h3><p style=\"margin:0 0 16px 0;font-size:13px;color:#666;font-weight:600;\">Comune — 1 punti vendita</p><div style=\"display:grid;grid-template-columns:repeat(3,1fr);gap:12px;text-align:center;\"><div><div style=\"width:52px;height:52px;border-radius:50%;background:#FFC72C;display:flex;align-items:center;justify-content:center;margin:0 auto;font-size:18px;font-weight:bold;color:#333;border:2px solid #FFC72C;\">1</div><div style=\"font-size:11px;margin-top:6px;color:#444;font-weight:600;line-height:1.2;\">McDonald's</div></div><div style=\"visibility:hidden;\"><div style=\"width:52px;height:52px;\"></div><div style=\"font-size:10px;\">-</div></div><div style=\"visibility:hidden;\"><div style=\"width:52px;height:52px;\"></div><div style=\"font-size:10px;\">-</div></div></div></div>","_regione":"Molise","_level":"comune","_umap_options":{"color":"#FFC72C","iconClass":"Circle"}}},{"type":"Feature","geometry":{"type":"Point","coordinates":[14.04111139679338,41.46891932649477]},"properties":{"name":"Venafro (1)","description":"<div style=\"font-family:'Nunito',Arial,sans-serif;max-width:320px;padding:8px;\"><h3 style=\"margin:0 0 6px 0;font-size:18px;color:#333;\">Venafro</h3><p style=\"margin:0 0 16px 0;font-size:13px;color:#666;font-weight:600;\">Comune — 1 punti vendita</p><div style=\"display:grid;grid-template-columns:repeat(3,1fr);gap:12px;text-align:center;\"><div><div style=\"width:52px;height:52px;border-radius:50%;background:#FFC72C;display:flex;align-items:center;justify-content:center;margin:0 auto;font-size:18px;font-weight:bold;color:#333;border:2px solid #FFC72C;\">1</div><div style=\"font-size:11px;margin-top:6px;color:#444;font-weight:600;line-height:1.2;\">McDonald's</div></div><div style=\"visibility:hidden;\"><div style=\"width:52px;height:52px;\"></div><div style=\"font-size:10px;\">-</div></div><div style=\"visibility:hidden;\"><div style=\"width:52px;height:52px;\"></div><div style=\"font-size:10px;\">-</div></div></div></div>","_regione":"Molise","_level":"comune","_umap_options":{"color":"#FFC72C","iconClass":"Circle"}}}]}