{"type":"FeatureCollection","features":[{"type":"Feature","geometry":{"type":"Point","coordinates":[14.662583024691116,41.56767163311976]},"properties":{"name":"Campobasso (1)","description":"<div style=\"font-family:Arial,sans-serif;max-width:320px;\"><h3 style=\"margin:0 0 4px 0;font-size:16px;\">Campobasso</h3><p style=\"margin:0 0 10px 0;font-size:12px;color:#666;\">Comune — 1 punti vendita</p><div style=\"display:grid;grid-template-columns:repeat(3,1fr);gap:10px 8px;text-align:center;\"><div><div style=\"width:52px;height:52px;border-radius:50%;background:#FFC72C;display:flex;align-items:center;justify-content:center;margin:0 auto;font-size:18px;font-weight:bold;color:#333;box-shadow:0 2px 6px rgba(0,0,0,0.2);\">1</div><div style=\"font-size:10px;margin-top:3px;color:#333;line-height:1.2;\">McDonald's</div></div><div style=\"visibility:hidden;\"><div style=\"width:52px;height:52px;\"></div><div style=\"font-size:10px;\">-</div></div><div style=\"visibility:hidden;\"><div style=\"width:52px;height:52px;\"></div><div style=\"font-size:10px;\">-</div></div></div></div>","_regione":"Molise","_level":"comune","_umap_options":{"color":"#FFC72C","iconClass":"Ball"}}},{"type":"Feature","geometry":{"type":"Point","coordinates":[14.216179508836648,41.60724606253518]},"properties":{"name":"Isernia (1)","description":"<div style=\"font-family:Arial,sans-serif;max-width:320px;\"><h3 style=\"margin:0 0 4px 0;font-size:16px;\">Isernia</h3><p style=\"margin:0 0 10px 0;font-size:12px;color:#666;\">Comune — 1 punti vendita</p><div style=\"display:grid;grid-template-columns:repeat(3,1fr);gap:10px 8px;text-align:center;\"><div><div style=\"width:52px;height:52px;border-radius:50%;background:#FFC72C;display:flex;align-items:center;justify-content:center;margin:0 auto;font-size:18px;font-weight:bold;color:#333;box-shadow:0 2px 6px rgba(0,0,0,0.2);\">1</div><div style=\"font-size:10px;margin-top:3px;color:#333;line-height:1.2;\">McDonald's</div></div><div style=\"visibility:hidden;\"><div style=\"width:52px;height:52px;\"></div><div style=\"font-size:10px;\">-</div></div><div style=\"visibility:hidden;\"><div style=\"width:52px;height:52px;\"></div><div style=\"font-size:10px;\">-</div></div></div></div>","_regione":"Molise","_level":"comune","_umap_options":{"color":"#FFC72C","iconClass":"Ball"}}},{"type":"Feature","geometry":{"type":"Point","coordinates":[14.04111139679338,41.46891932649477]},"properties":{"name":"Venafro (1)","description":"<div style=\"font-family:Arial,sans-serif;max-width:320px;\"><h3 style=\"margin:0 0 4px 0;font-size:16px;\">Venafro</h3><p style=\"margin:0 0 10px 0;font-size:12px;color:#666;\">Comune — 1 punti vendita</p><div style=\"display:grid;grid-template-columns:repeat(3,1fr);gap:10px 8px;text-align:center;\"><div><div style=\"width:52px;height:52px;border-radius:50%;background:#FFC72C;display:flex;align-items:center;justify-content:center;margin:0 auto;font-size:18px;font-weight:bold;color:#333;box-shadow:0 2px 6px rgba(0,0,0,0.2);\">1</div><div style=\"font-size:10px;margin-top:3px;color:#333;line-height:1.2;\">McDonald's</div></div><div style=\"visibility:hidden;\"><div style=\"width:52px;height:52px;\"></div><div style=\"font-size:10px;\">-</div></div><div style=\"visibility:hidden;\"><div style=\"width:52px;height:52px;\"></div><div style=\"font-size:10px;\">-</div></div></div></div>","_regione":"Molise","_level":"comune","_umap_options":{"color":"#FFC72C","iconClass":"Ball"}}}]}